geoana/plotting_utils.py
geoana/shapes.py
geoana/__init__.py
geoana/spatial.py
geoana/gravity.py
geoana/utils.py
geoana/kernels/__init__.py
geoana/kernels/tranverse_electric_reflections.py
geoana/kernels/potential_field_prism.py
geoana/kernels/_extensions/potential_field_prism.cpython-313-darwin.so
geoana/kernels/_extensions/__init__.py
geoana/kernels/_extensions/rTE.cpython-313-darwin.so
geoana/em/__init__.py
geoana/em/base.py
geoana/em/tdem/halfspace.py
geoana/em/tdem/simple_functions.py
geoana/em/tdem/__init__.py
geoana/em/tdem/wholespace.py
geoana/em/tdem/reference.py
geoana/em/tdem/base.py
geoana/em/fdem/layered.py
geoana/em/fdem/halfspace.py
geoana/em/fdem/simple_functions.py
geoana/em/fdem/__init__.py
geoana/em/fdem/wholespace.py
geoana/em/fdem/base.py
geoana/em/static/halfspace.py
geoana/em/static/__init__.py
geoana/em/static/freespace.py
geoana/em/static/wholespace.py
geoana/em/static/sphere.py
geoana/earthquake/__init__.py
geoana/earthquake/oksar.py
geoana-0.8.0.dist-info/RECORD
geoana-0.8.0.dist-info/LICENSE
geoana-0.8.0.dist-info/WHEEL
geoana-0.8.0.dist-info/METADATA
