Metadata-Version: 2.1
Name: geoana
Version: 0.8.0
Summary: Analytic expressions for geophysical responses
Keywords: geophysics,electromagnetics,gravity,magnetics
Author-Email: SimPEG developers <lindseyheagy@gmail.com>
License: MIT License
Classifier: Development Status :: 4 - Beta
Classifier: Intended Audience :: Education
Classifier: Intended Audience :: Science/Research
Classifier: License :: OSI Approved :: MIT License
Classifier: Programming Language :: Python
Classifier: Programming Language :: Cython
Classifier: Topic :: Scientific/Engineering
Classifier: Topic :: Scientific/Engineering :: Mathematics
Classifier: Topic :: Scientific/Engineering :: Physics
Classifier: Operating System :: Microsoft :: Windows
Classifier: Operating System :: POSIX
Classifier: Operating System :: Unix
Classifier: Operating System :: MacOS
Classifier: Natural Language :: English
Project-URL: Homepage, https://simpeg.xyz
Project-URL: Documentation, https://geoana.simpeg.xyz
Project-URL: Repository, https://github.com/simpeg/geoana.git
Requires-Python: >=3.11
Requires-Dist: numpy>=1.22.4
Requires-Dist: scipy>=1.12
Requires-Dist: libdlf
Provides-Extra: plot
Requires-Dist: matplotlib; extra == "plot"
Provides-Extra: extras
Requires-Dist: utm; extra == "extras"
Provides-Extra: jittable
Requires-Dist: numba; extra == "jittable"
Provides-Extra: all
Requires-Dist: geoana[extras,jittable,plot]; extra == "all"
Provides-Extra: doc
Requires-Dist: sphinx==8.1.3; extra == "doc"
Requires-Dist: pydata-sphinx-theme==0.16.1; extra == "doc"
Requires-Dist: sphinx-gallery==0.19.0; extra == "doc"
Requires-Dist: numpydoc==1.9.0; extra == "doc"
Requires-Dist: jupyter; extra == "doc"
Requires-Dist: graphviz; extra == "doc"
Requires-Dist: pillow; extra == "doc"
Requires-Dist: geoana[all]; extra == "doc"
Provides-Extra: test
Requires-Dist: pytest; extra == "test"
Requires-Dist: pytest-cov; extra == "test"
Requires-Dist: sympy; extra == "test"
Requires-Dist: discretize; extra == "test"
Requires-Dist: requests; extra == "test"
Requires-Dist: geoana[all,doc]; extra == "test"
Provides-Extra: build
Requires-Dist: meson-python>=0.15.0; extra == "build"
Requires-Dist: meson; extra == "build"
Requires-Dist: ninja; extra == "build"
Requires-Dist: numpy>=2.0.0rc1; extra == "build"
Requires-Dist: cython>=3.1.0; extra == "build"
Requires-Dist: setuptools_scm; extra == "build"
